[{"player_card_value":97,"enemy_card_value":70,"center_mod":2.7,"enemy_mod":1.4,"shield_mod":2.2,"freeze_mod":0.6,"rock_mod":0.8,"mmr":-26.665},{"player_card_value":97,"enemy_card_value":70,"center_mod":2.7,"enemy_mod":1.4,"shield_mod":2.2,"freeze_mod":0.6,"rock_mod":0.8,"mmr":-26.665},{"player_card_value":97,"enemy_card_value":70,"center_mod":2.7,"enemy_mod":1.4,"shield_mod":2.2,"freeze_mod":0.6,"rock_mod":0.8,"mmr":28.335},{"player_card_value":97,"enemy_card_value":70,"center_mod":2.7,"enemy_mod":1.4,"shield_mod":2.2,"freeze_mod":0.6,"rock_mod":0.8,"mmr":-26.665},{"player_card_value":97,"enemy_card_value":70,"center_mod":2.7,"enemy_mod":1.4,"shield_mod":2.2,"freeze_mod":0.6,"rock_mod":0.8,"mmr":28.335},{"player_card_value":97,"enemy_card_value":70,"center_mod":2.7,"enemy_mod":1.4,"shield_mod":2.2,"freeze_mod":0.6,"rock_mod":0.8,"mmr":-26.665},{"player_card_value":97,"enemy_card_value":70,"center_mod":2.7,"enemy_mod":1.4,"shield_mod":2.2,"freeze_mod":0.6,"rock_mod":0.8,"mmr":-26.665},{"player_card_value":97,"enemy_card_value":70,"center_mod":2.7,"enemy_mod":1.4,"shield_mod":2.2,"freeze_mod":0.6,"rock_mod":0.8,"mmr":28.335},{"player_card_value":97,"enemy_card_value":70,"center_mod":2.7,"enemy_mod":1.4,"shield_mod":2.2,"freeze_mod":0.6,"rock_mod":0.8,"mmr":-26.665},{"player_card_value":97,"enemy_card_value":70,"center_mod":2.7,"enemy_mod":1.4,"shield_mod":2.2,"freeze_mod":0.6,"rock_mod":0.8,"mmr":28.335},{"player_card_value":97,"enemy_card_value":70,"center_mod":2.7,"enemy_mod":1.4,"shield_mod":2.2,"freeze_mod":0.6,"rock_mod":0.8,"mmr":28.335},{"player_card_value":97,"enemy_card_value":70,"center_mod":2.7,"enemy_mod":1.4,"shield_mod":2.2,"freeze_mod":0.6,"rock_mod":0.8,"mmr":-26.665},{"player_card_value":97,"enemy_card_value":70,"center_mod":2.7,"enemy_mod":1.4,"shield_mod":2.2,"freeze_mod":0.6,"rock_mod":0.8,"mmr":-26.665},{"player_card_value":97,"enemy_card_value":70,"center_mod":2.7,"enemy_mod":1.4,"shield_mod":2.2,"freeze_mod":0.6,"rock_mod":0.8,"mmr":28.335},{"player_card_value":97,"enemy_card_value":70,"center_mod":2.7,"enemy_mod":1.4,"shield_mod":2.2,"freeze_mod":0.6,"rock_mod":0.8,"mmr":-26.665},{"player_card_value":97,"enemy_card_value":70,"center_mod":2.7,"enemy_mod":1.4,"shield_mod":2.2,"freeze_mod":0.6,"rock_mod":0.8,"mmr":28.335},{"player_card_value":97,"enemy_card_value":70,"center_mod":2.7,"enemy_mod":1.4,"shield_mod":2.2,"freeze_mod":0.6,"rock_mod":0.8,"mmr":-26.665},{"player_card_value":97,"enemy_card_value":70,"center_mod":2.7,"enemy_mod":1.4,"shield_mod":2.2,"freeze_mod":0.6,"rock_mod":0.8,"mmr":28.335},{"player_card_value":97,"enemy_card_value":70,"center_mod":2.7,"enemy_mod":1.4,"shield_mod":2.2,"freeze_mod":0.6,"rock_mod":0.8,"mmr":28.335},{"player_card_value":97,"enemy_card_value":70,"center_mod":2.7,"enemy_mod":1.4,"shield_mod":2.2,"freeze_mod":0.6,"rock_mod":0.8,"mmr":-26.665},{"player_card_value":97,"enemy_card_value":70,"center_mod":1.9,"enemy_mod":1.4,"shield_mod":1.8,"freeze_mod":0.6,"rock_mod":0.8,"mmr":28.335},{"player_card_value":97,"enemy_card_value":70,"center_mod":1.9,"enemy_mod":1.4,"shield_mod":1.8,"freeze_mod":0.6,"rock_mod":0.8,"mmr":28.335},{"player_card_value":97,"enemy_card_value":70,"center_mod":1.9,"enemy_mod":1.4,"shield_mod":1.8,"freeze_mod":0.6,"rock_mod":0.8,"mmr":28.335},{"player_card_value":97,"enemy_card_value":70,"center_mod":1.9,"enemy_mod":1.4,"shield_mod":1.8,"freeze_mod":0.6,"rock_mod":0.8,"mmr":-26.665},{"player_card_value":97,"enemy_card_value":70,"center_mod":1.9,"enemy_mod":1.4,"shield_mod":1.8,"freeze_mod":0.6,"rock_mod":0.8,"mmr":-26.665},{"player_card_value":97,"enemy_card_value":70,"center_mod":1.9,"enemy_mod":1.4,"shield_mod":1.8,"freeze_mod":0.6,"rock_mod":0.8,"mmr":28.335},{"player_card_value":97,"enemy_card_value":70,"center_mod":1.9,"enemy_mod":1.4,"shield_mod":1.8,"freeze_mod":0.6,"rock_mod":0.8,"mmr":28.335},{"player_card_value":97,"enemy_card_value":70,"center_mod":1.9,"enemy_mod":1.4,"shield_mod":1.8,"freeze_mod":0.6,"rock_mod":0.8,"mmr":-26.665},{"player_card_value":97,"enemy_card_value":70,"center_mod":1.9,"enemy_mod":1.4,"shield_mod":1.8,"freeze_mod":0.6,"rock_mod":0.8,"mmr":-26.665},{"player_card_value":97,"enemy_card_value":70,"center_mod":1.9,"enemy_mod":1.4,"shield_mod":1.8,"freeze_mod":0.6,"rock_mod":0.8,"mmr":28.335},{"player_card_value":97,"enemy_card_value":70,"center_mod":1.9,"enemy_mod":1.4,"shield_mod":1.8,"freeze_mod":0.6,"rock_mod":0.8,"mmr":-26.665},{"player_card_value":97,"enemy_card_value":70,"center_mod":1.9,"enemy_mod":1.4,"shield_mod":1.8,"freeze_mod":0.6,"rock_mod":0.8,"mmr":28.335},{"player_card_value":97,"enemy_card_value":70,"center_mod":1.9,"enemy_mod":1.4,"shield_mod":1.8,"freeze_mod":0.6,"rock_mod":0.8,"mmr":-26.665},{"player_card_value":97,"enemy_card_value":70,"center_mod":1.9,"enemy_mod":1.4,"shield_mod":1.8,"freeze_mod":0.6,"rock_mod":0.8,"mmr":28.335},{"player_card_value":97,"enemy_card_value":70,"center_mod":1.9,"enemy_mod":1.4,"shield_mod":1.8,"freeze_mod":0.6,"rock_mod":0.8,"mmr":28.335},{"player_card_value":97,"enemy_card_value":70,"center_mod":1.9,"enemy_mod":1.4,"shield_mod":1.8,"freeze_mod":0.6,"rock_mod":0.8,"mmr":-26.665},{"player_card_value":97,"enemy_card_value":70,"center_mod":1.9,"enemy_mod":1.4,"shield_mod":1.8,"freeze_mod":0.6,"rock_mod":0.8,"mmr":-26.665},{"player_card_value":97,"enemy_card_value":70,"center_mod":1.9,"enemy_mod":1.4,"shield_mod":1.8,"freeze_mod":0.6,"rock_mod":0.8,"mmr":28.335},{"player_card_value":97,"enemy_card_value":70,"center_mod":1.9,"enemy_mod":1.4,"shield_mod":1.8,"freeze_mod":0.6,"rock_mod":0.8,"mmr":0.17300000000000182},{"player_card_value":97,"enemy_card_value":70,"center_mod":1.9,"enemy_mod":1.4,"shield_mod":1.8,"freeze_mod":0.6,"rock_mod":0.8,"mmr":1.1730000000000018},{"player_card_value":97,"enemy_card_value":70,"center_mod":1.9,"enemy_mod":1.4,"shield_mod":1.8,"freeze_mod":0.6,"rock_mod":0.8,"mmr":55.173},{"player_card_value":97,"enemy_card_value":70,"center_mod":1.9,"enemy_mod":1.4,"shield_mod":1.8,"freeze_mod":0.6,"rock_mod":0.8,"mmr":-53.827},{"player_card_value":97,"enemy_card_value":70,"center_mod":1.9,"enemy_mod":1.4,"shield_mod":1.8,"freeze_mod":0.6,"rock_mod":0.8,"mmr":0.17300000000000182},{"player_card_value":97,"enemy_card_value":70,"center_mod":1.9,"enemy_mod":1.4,"shield_mod":1.8,"freeze_mod":0.6,"rock_mod":0.8,"mmr":1.1730000000000018},{"player_card_value":97,"enemy_card_value":70,"center_mod":1.9,"enemy_mod":1.4,"shield_mod":1.8,"freeze_mod":0.6,"rock_mod":0.8,"mmr":55.173},{"player_card_value":97,"enemy_card_value":70,"center_mod":1.9,"enemy_mod":1.4,"shield_mod":1.8,"freeze_mod":0.6,"rock_mod":0.8,"mmr":-25.485999999999997},{"player_card_value":97,"enemy_card_value":70,"center_mod":1.9,"enemy_mod":1.4,"shield_mod":1.8,"freeze_mod":0.6,"rock_mod":0.8,"mmr":-53.827},{"player_card_value":97,"enemy_card_value":70,"center_mod":1.9,"enemy_mod":1.4,"shield_mod":1.8,"freeze_mod":0.6,"rock_mod":0.8,"mmr":55.173},{"player_card_value":97,"enemy_card_value":70,"center_mod":1.9,"enemy_mod":1.4,"shield_mod":1.8,"freeze_mod":0.6,"rock_mod":0.8,"mmr":28.335},{"player_card_value":97,"enemy_card_value":70,"center_mod":1.9,"enemy_mod":1.4,"shield_mod":1.8,"freeze_mod":0.6,"rock_mod":0.8,"mmr":-26.665},{"player_card_value":97,"enemy_card_value":70,"center_mod":1.9,"enemy_mod":1.4,"shield_mod":1.8,"freeze_mod":0.6,"rock_mod":0.8,"mmr":28.335},{"player_card_value":97,"enemy_card_value":70,"center_mod":1.9,"enemy_mod":1.4,"shield_mod":1.8,"freeze_mod":0.6,"rock_mod":0.8,"mmr":-26.665},{"player_card_value":97,"enemy_card_value":70,"center_mod":1.9,"enemy_mod":1.4,"shield_mod":1.8,"freeze_mod":0.6,"rock_mod":0.8,"mmr":28.335},{"player_card_value":97,"enemy_card_value":70,"center_mod":1.9,"enemy_mod":1.4,"shield_mod":1.8,"freeze_mod":0.6,"rock_mod":0.8,"mmr":-26.665},{"player_card_value":97,"enemy_card_value":70,"center_mod":1.9,"enemy_mod":1.4,"shield_mod":1.8,"freeze_mod":0.6,"rock_mod":0.8,"mmr":26.514000000000003},{"player_card_value":97,"enemy_card_value":70,"center_mod":1.9,"enemy_mod":1.4,"shield_mod":1.8,"freeze_mod":0.6,"rock_mod":0.8,"mmr":-51.641999999999996},{"player_card_value":97,"enemy_card_value":70,"center_mod":1.9,"enemy_mod":1.4,"shield_mod":1.8,"freeze_mod":0.6,"rock_mod":0.8,"mmr":28.335},{"player_card_value":97,"enemy_card_value":70,"center_mod":1.9,"enemy_mod":1.4,"shield_mod":1.8,"freeze_mod":0.6,"rock_mod":0.8,"mmr":-26.665},{"player_card_value":97,"enemy_card_value":70,"center_mod":1.9,"enemy_mod":1.4,"shield_mod":1.8,"freeze_mod":0.6,"rock_mod":0.8,"mmr":55.173},{"player_card_value":97,"enemy_card_value":70,"center_mod":1.9,"enemy_mod":1.4,"shield_mod":1.8,"freeze_mod":0.6,"rock_mod":0.8,"mmr":-53.827},{"player_card_value":97,"enemy_card_value":70,"center_mod":1.9,"enemy_mod":1.4,"shield_mod":1.8,"freeze_mod":0.6,"rock_mod":0.8,"mmr":-53.827},{"player_card_value":97,"enemy_card_value":70,"center_mod":1.9,"enemy_mod":1.4,"shield_mod":1.8,"freeze_mod":0.6,"rock_mod":0.8,"mmr":55.173},{"player_card_value":97,"enemy_card_value":70,"center_mod":1.9,"enemy_mod":1.4,"shield_mod":1.8,"freeze_mod":0.6,"rock_mod":0.8,"mmr":28.335},{"player_card_value":97,"enemy_card_value":70,"center_mod":1.9,"enemy_mod":1.4,"shield_mod":1.8,"freeze_mod":0.6,"rock_mod":0.8,"mmr":-53.827},{"player_card_value":97,"enemy_card_value":70,"center_mod":1.9,"enemy_mod":1.4,"shield_mod":1.8,"freeze_mod":0.6,"rock_mod":0.8,"mmr":-53.827},{"player_card_value":97,"enemy_card_value":70,"center_mod":1.9,"enemy_mod":1.4,"shield_mod":1.8,"freeze_mod":0.6,"rock_mod":0.8,"mmr":0.17300000000000182},{"player_card_value":97,"enemy_card_value":70,"center_mod":1.9,"enemy_mod":1.4,"shield_mod":1.8,"freeze_mod":0.6,"rock_mod":0.8,"mmr":-80.48599999999999},{"player_card_value":97,"enemy_card_value":70,"center_mod":1.9,"enemy_mod":1.4,"shield_mod":1.8,"freeze_mod":0.6,"rock_mod":0.8,"mmr":26.514000000000003},{"player_card_value":97,"enemy_card_value":70,"center_mod":1.9,"enemy_mod":1.4,"shield_mod":1.8,"freeze_mod":0.6,"rock_mod":0.8,"mmr":1.1730000000000018},{"player_card_value":97,"enemy_card_value":70,"center_mod":1.9,"enemy_mod":1.4,"shield_mod":1.8,"freeze_mod":0.6,"rock_mod":0.8,"mmr":55.173},{"player_card_value":97,"enemy_card_value":70,"center_mod":1.9,"enemy_mod":1.4,"shield_mod":1.8,"freeze_mod":0.6,"rock_mod":0.8,"mmr":81.51400000000001},{"player_card_value":97,"enemy_card_value":70,"center_mod":1.9,"enemy_mod":1.4,"shield_mod":1.8,"freeze_mod":0.6,"rock_mod":0.8,"mmr":-53.827},{"player_card_value":97,"enemy_card_value":70,"center_mod":1.9,"enemy_mod":1.4,"shield_mod":1.8,"freeze_mod":0.6,"rock_mod":0.8,"mmr":81.51400000000001},{"player_card_value":97,"enemy_card_value":70,"center_mod":1.9,"enemy_mod":1.4,"shield_mod":1.8,"freeze_mod":0.6,"rock_mod":0.8,"mmr":-80.48599999999999},{"player_card_value":97,"enemy_card_value":70,"center_mod":1.9,"enemy_mod":1.4,"shield_mod":1.8,"freeze_mod":0.6,"rock_mod":0.8,"mmr":-106.642},{"player_card_value":97,"enemy_card_value":70,"center_mod":1.9,"enemy_mod":1.4,"shield_mod":1.8,"freeze_mod":0.6,"rock_mod":0.8,"mmr":26.514000000000003},{"player_card_value":97,"enemy_card_value":70,"center_mod":1.9,"enemy_mod":1.4,"shield_mod":1.8,"freeze_mod":0.6,"rock_mod":0.8,"mmr":-53.827},{"player_card_value":97,"enemy_card_value":70,"center_mod":1.9,"enemy_mod":1.4,"shield_mod":1.8,"freeze_mod":0.6,"rock_mod":0.8,"mmr":52.358000000000004},{"player_card_value":97,"enemy_card_value":70,"center_mod":1.9,"enemy_mod":1.4,"shield_mod":1.8,"freeze_mod":0.6,"rock_mod":0.8,"mmr":55.173},{"player_card_value":97,"enemy_card_value":70,"center_mod":1.9,"enemy_mod":1.4,"shield_mod":1.8,"freeze_mod":0.6,"rock_mod":0.8,"mmr":-80.48599999999999},{"player_card_value":97,"enemy_card_value":70,"center_mod":1.9,"enemy_mod":1.4,"shield_mod":1.8,"freeze_mod":0.6,"rock_mod":0.8,"mmr":55.173},{"player_card_value":97,"enemy_card_value":70,"center_mod":1.9,"enemy_mod":1.4,"shield_mod":1.8,"freeze_mod":0.6,"rock_mod":0.8,"mmr":-53.827},{"player_card_value":97,"enemy_card_value":70,"center_mod":1.9,"enemy_mod":1.4,"shield_mod":1.8,"freeze_mod":0.6,"rock_mod":0.8,"mmr":81.51400000000001},{"player_card_value":97,"enemy_card_value":70,"center_mod":1.9,"enemy_mod":1.4,"shield_mod":1.8,"freeze_mod":0.6,"rock_mod":0.8,"mmr":-80.48599999999999},{"player_card_value":97,"enemy_card_value":70,"center_mod":1.9,"enemy_mod":1.4,"shield_mod":1.8,"freeze_mod":0.6,"rock_mod":0.8,"mmr":55.173},{"player_card_value":97,"enemy_card_value":70,"center_mod":1.9,"enemy_mod":1.4,"shield_mod":1.8,"freeze_mod":0.6,"rock_mod":0.8,"mmr":-80.48599999999999},{"player_card_value":97,"enemy_card_value":70,"center_mod":1.9,"enemy_mod":1.4,"shield_mod":1.8,"freeze_mod":0.6,"rock_mod":0.8,"mmr":-132.295},{"player_card_value":97,"enemy_card_value":70,"center_mod":1.9,"enemy_mod":1.4,"shield_mod":1.8,"freeze_mod":0.6,"rock_mod":0.8,"mmr":107.358},{"player_card_value":97,"enemy_card_value":70,"center_mod":1.9,"enemy_mod":1.4,"shield_mod":1.8,"freeze_mod":0.6,"rock_mod":0.8,"mmr":55.173},{"player_card_value":97,"enemy_card_value":70,"center_mod":1.9,"enemy_mod":1.4,"shield_mod":1.8,"freeze_mod":0.6,"rock_mod":0.8,"mmr":-77.29499999999999},{"player_card_value":97,"enemy_card_value":70,"center_mod":1.9,"enemy_mod":1.4,"shield_mod":1.8,"freeze_mod":0.6,"rock_mod":0.8,"mmr":77.70500000000001},{"player_card_value":97,"enemy_card_value":70,"center_mod":1.9,"enemy_mod":1.4,"shield_mod":1.8,"freeze_mod":0.6,"rock_mod":0.8,"mmr":-106.642},{"player_card_value":97,"enemy_card_value":70,"center_mod":1.9,"enemy_mod":1.4,"shield_mod":1.8,"freeze_mod":0.6,"rock_mod":0.8,"mmr":-80.48599999999999},{"player_card_value":97,"enemy_card_value":70,"center_mod":1.9,"enemy_mod":1.4,"shield_mod":1.8,"freeze_mod":0.6,"rock_mod":0.8,"mmr":81.51400000000001},{"player_card_value":97,"enemy_card_value":70,"center_mod":1.9,"enemy_mod":1.4,"shield_mod":1.8,"freeze_mod":0.6,"rock_mod":0.8,"mmr":81.51400000000001},{"player_card_value":97,"enemy_card_value":70,"center_mod":1.9,"enemy_mod":1.4,"shield_mod":1.8,"freeze_mod":0.6,"rock_mod":0.8,"mmr":-106.642},{"player_card_value":97,"enemy_card_value":70,"center_mod":1.9,"enemy_mod":1.4,"shield_mod":1.8,"freeze_mod":0.6,"rock_mod":0.8,"mmr":132.705},{"player_card_value":97,"enemy_card_value":70,"center_mod":1.9,"enemy_mod":1.4,"shield_mod":1.8,"freeze_mod":0.6,"rock_mod":0.8,"mmr":-102.445},{"player_card_value":97,"enemy_card_value":70,"center_mod":1.9,"enemy_mod":1.4,"shield_mod":1.8,"freeze_mod":0.6,"rock_mod":0.8,"mmr":-157.445},{"player_card_value":97,"enemy_card_value":70,"center_mod":1.9,"enemy_mod":1.4,"shield_mod":1.8,"freeze_mod":0.6,"rock_mod":0.8,"mmr":81.51400000000001},{"player_card_value":97,"enemy_card_value":70,"center_mod":1.9,"enemy_mod":1.4,"shield_mod":1.8,"freeze_mod":0.6,"rock_mod":0.8,"mmr":107.358},{"player_card_value":97,"enemy_card_value":70,"center_mod":1.9,"enemy_mod":1.4,"shield_mod":1.8,"freeze_mod":0.6,"rock_mod":0.8,"mmr":-106.642},{"player_card_value":97,"enemy_card_value":70,"center_mod":1.9,"enemy_mod":1.4,"shield_mod":1.8,"freeze_mod":0.6,"rock_mod":0.8,"mmr":81.51400000000001},{"player_card_value":97,"enemy_card_value":70,"center_mod":1.9,"enemy_mod":1.4,"shield_mod":1.8,"freeze_mod":0.6,"rock_mod":0.8,"mmr":-80.48599999999999},{"player_card_value":97,"enemy_card_value":70,"center_mod":1.9,"enemy_mod":1.4,"shield_mod":1.8,"freeze_mod":0.6,"rock_mod":0.8,"mmr":-132.295},{"player_card_value":97,"enemy_card_value":70,"center_mod":1.9,"enemy_mod":1.4,"shield_mod":1.8,"freeze_mod":0.6,"rock_mod":0.8,"mmr":81.51400000000001},{"player_card_value":97,"enemy_card_value":70,"center_mod":1.9,"enemy_mod":1.4,"shield_mod":1.8,"freeze_mod":0.6,"rock_mod":0.8,"mmr":52.358000000000004},{"player_card_value":97,"enemy_card_value":70,"center_mod":1.9,"enemy_mod":1.4,"shield_mod":1.8,"freeze_mod":0.6,"rock_mod":0.8,"mmr":-80.48599999999999},{"player_card_value":97,"enemy_card_value":70,"center_mod":1.9,"enemy_mod":1.4,"shield_mod":1.8,"freeze_mod":0.6,"rock_mod":0.8,"mmr":-132.295},{"player_card_value":97,"enemy_card_value":70,"center_mod":1.9,"enemy_mod":1.4,"shield_mod":1.8,"freeze_mod":0.6,"rock_mod":0.8,"mmr":107.358},{"player_card_value":97,"enemy_card_value":70,"center_mod":1.9,"enemy_mod":1.4,"shield_mod":1.8,"freeze_mod":0.6,"rock_mod":0.8,"mmr":-106.642},{"player_card_value":97,"enemy_card_value":70,"center_mod":1.9,"enemy_mod":1.4,"shield_mod":1.8,"freeze_mod":0.6,"rock_mod":0.8,"mmr":132.705},{"player_card_value":97,"enemy_card_value":70,"center_mod":1.9,"enemy_mod":1.4,"shield_mod":1.8,"freeze_mod":0.6,"rock_mod":0.8,"mmr":107.358},{"player_card_value":97,"enemy_card_value":70,"center_mod":1.9,"enemy_mod":1.4,"shield_mod":1.8,"freeze_mod":0.6,"rock_mod":0.8,"mmr":-106.642},{"player_card_value":97,"enemy_card_value":70,"center_mod":1.9,"enemy_mod":1.4,"shield_mod":1.8,"freeze_mod":0.6,"rock_mod":0.8,"mmr":52.358000000000004},{"player_card_value":97,"enemy_card_value":70,"center_mod":1.9,"enemy_mod":1.4,"shield_mod":1.8,"freeze_mod":0.6,"rock_mod":0.8,"mmr":-25.485999999999997},{"player_card_value":97,"enemy_card_value":70,"center_mod":1.9,"enemy_mod":1.4,"shield_mod":1.8,"freeze_mod":0.6,"rock_mod":0.8,"mmr":55.35800000000001},{"player_card_value":97,"enemy_card_value":70,"center_mod":1.9,"enemy_mod":1.4,"shield_mod":1.8,"freeze_mod":0.6,"rock_mod":0.8,"mmr":-81.29499999999999},{"player_card_value":97,"enemy_card_value":70,"center_mod":1.9,"enemy_mod":1.4,"shield_mod":1.8,"freeze_mod":0.6,"rock_mod":0.8,"mmr":107.358},{"player_card_value":97,"enemy_card_value":70,"center_mod":1.9,"enemy_mod":1.4,"shield_mod":1.8,"freeze_mod":0.6,"rock_mod":0.8,"mmr":-127.09199999999998},{"player_card_value":97,"enemy_card_value":70,"center_mod":1.9,"enemy_mod":1.4,"shield_mod":1.8,"freeze_mod":0.6,"rock_mod":0.8,"mmr":-157.445},{"player_card_value":97,"enemy_card_value":70,"center_mod":1.9,"enemy_mod":1.4,"shield_mod":1.8,"freeze_mod":0.6,"rock_mod":0.8,"mmr":107.358},{"player_card_value":97,"enemy_card_value":70,"center_mod":1.9,"enemy_mod":1.4,"shield_mod":1.8,"freeze_mod":0.6,"rock_mod":0.8,"mmr":132.705},{"player_card_value":97,"enemy_card_value":70,"center_mod":1.9,"enemy_mod":1.4,"shield_mod":1.8,"freeze_mod":0.6,"rock_mod":0.8,"mmr":-51.641999999999996},{"player_card_value":97,"enemy_card_value":70,"center_mod":1.9,"enemy_mod":1.4,"shield_mod":1.8,"freeze_mod":0.6,"rock_mod":0.8,"mmr":-182.09199999999998},{"player_card_value":97,"enemy_card_value":70,"center_mod":1.9,"enemy_mod":1.4,"shield_mod":1.8,"freeze_mod":0.6,"rock_mod":0.8,"mmr":157.555},{"player_card_value":97,"enemy_card_value":70,"center_mod":1.9,"enemy_mod":1.4,"shield_mod":1.8,"freeze_mod":0.6,"rock_mod":0.8,"mmr":-132.295},{"player_card_value":97,"enemy_card_value":70,"center_mod":1.9,"enemy_mod":1.4,"shield_mod":1.8,"freeze_mod":0.6,"rock_mod":0.8,"mmr":132.705},{"player_card_value":97,"enemy_card_value":70,"center_mod":1.9,"enemy_mod":1.4,"shield_mod":1.8,"freeze_mod":0.6,"rock_mod":0.8,"mmr":-206.236},{"player_card_value":97,"enemy_card_value":70,"center_mod":1.9,"enemy_mod":1.4,"shield_mod":1.8,"freeze_mod":0.6,"rock_mod":0.8,"mmr":157.555},{"player_card_value":97,"enemy_card_value":70,"center_mod":1.9,"enemy_mod":1.4,"shield_mod":1.8,"freeze_mod":0.6,"rock_mod":0.8,"mmr":28.335}]